miniclient/miniclient.py
tracim_daemon_sdk/__init__.py
tracim_daemon_sdk/daemon_event.py
tracim_daemon_sdk/data.py
tracim_daemon_sdk/event.py
tracim_daemon_sdk/helper.py
tracim_daemon_sdk/sdk.py
tracim_daemon_sdk-1.0.3.dist-info/LICENCE
tracim_daemon_sdk-1.0.3.dist-info/METADATA
tracim_daemon_sdk-1.0.3.dist-info/WHEEL
tracim_daemon_sdk-1.0.3.dist-info/top_level.txt
tracim_daemon_sdk-1.0.3.dist-info/RECORD
