Metadata-Version: 2.1
Name: tracim-daemon-sdk
Version: 1.0.3
Summary: An SDK for the TracimDaemon project
Author-email: Millefeuille <1kfeuille@mlabouri.fr>
Project-URL: Homepage, https://github.com/Millefeuille42/TracimDaemonSDK_Python
Project-URL: Bug Tracker, https://github.com/Millefeuille42/TracimDaemonSDK_Python/issues
Classifier: Programming Language :: Python :: 3
Classifier: License :: OSI Approved :: MIT License
Classifier: Operating System :: OS Independent
Requires-Python: >=3.7
License-File: LICENCE
